conf/__init__.py
conf/configuration.py
topic_modeling/__init__.py
topic_modeling/model_corpora.py
topic_modeling/model_corpus_args_me.py
topic_modeling/model_corpus_args_me_cluster.py
topic_modeling/model_corpus_ibm_debate_claim_sentence_search.py
topic_modeling/model_corpus_utdallas_icle_essay_scoring.py
topic_modeling/topic_modeling.py
topic_modeling/topics.py
topic_modeling/validate_cluster_topic_modeling.py
topic_ontologies-0.2.0.dist-info/LICENSE
topic_ontologies-0.2.0.dist-info/METADATA
topic_ontologies-0.2.0.dist-info/WHEEL
topic_ontologies-0.2.0.dist-info/top_level.txt
topic_ontologies-0.2.0.dist-info/RECORD
